cask/__init__.py
cask/cli.py
cask/package.py
cask/store.py
cask/test/install_script.sh
cask/test/test.yaml
cask/test/test_init.py
cask/test/test_main.py
cask/test/test_object.py
cask/test/test_tmp.py
cask/test/testcask.caskpkg
cask/test/testfunc.dill
cask/test/logtest/logtest.txt
shihua_cask-0.1.dist-info/LICENSE
shihua_cask-0.1.dist-info/METADATA
shihua_cask-0.1.dist-info/WHEEL
shihua_cask-0.1.dist-info/entry_points.txt
shihua_cask-0.1.dist-info/top_level.txt
shihua_cask-0.1.dist-info/RECORD
