Metadata-Version: 2.1
Name: shihua-cask
Version: 0.1
Summary: Cash is a storage management tool, including project packaging and remote storage.
Home-page: https://github.com/redblue0216/Cask
Author: shihua
Author-email: 15021408795@163.com
License: MIT
Platform: UNKNOWN
Requires-Python: >=3.9.12
License-File: LICENSE
